[
    {
        "id": "9527",
        "name": "Github 歌单",
        "cover": "images/album.png",
        "creatorName": "EXP",
        "creatorAvatar": "images/avatar.jpg",
        "item": [
            {
                "id": "196af2d2dd85526cfa0c679a6dcfc868",
                "name": "بالدۇر ئويغانغان ئادەم 3 .قىسىم  (ئاۋازلىق ئەسەر)",
                "artist": "ئاۋازلىق ئەسەر Awazliq Eser",
                "album": "بالدۇر ئويغانغان ئادەم 3 .قىسىم  (ئاۋازلىق ئەسەر)",
                "url": "static/Baldur Oyghan'ghan Adem/بالدۇر ئويغانغان ئادەم 3 .قىسىم  (ئاۋازلىق ئەسەر).mp3",
                "pic": "",
                "lyric": "",
                "source": "local",
                "url_id": "196af2d2dd85526cfa0c679a6dcfc868",
                "pic_id": "",
                "lyric_id": ""
            },
            {
                "id": "975f53d7413e5efe971149529a52de2a",
                "name": "بالدۇر ئويغانغان ئادەم مۇقەددىمە  (ئاۋازلىق ئەسەر)",
                "artist": "ئاۋازلىق ئەسەر Awazliq Eser",
                "album": "بالدۇر ئويغانغان ئادەم مۇقەددىمە  (ئاۋازلىق ئەسەر)",
                "url": "static/Baldur Oyghan'ghan Adem/بالدۇر ئويغانغان ئادەم مۇقەددىمە  (ئاۋازلىق ئەسەر).mp3",
                "pic": "",
                "lyric": "",
                "source": "local",
                "url_id": "975f53d7413e5efe971149529a52de2a",
                "pic_id": "",
                "lyric_id": ""
            },
            {
                "id": "3089f1bd7ea1e8ebcaea2de32093f5c5",
                "name": "بالدۇر ئويغانغان ئادەم 4 .قىسىم  (ئاۋازلىق ئەسەر)",
                "artist": "ئاۋازلىق ئەسەر Awazliq Eser",
                "album": "بالدۇر ئويغانغان ئادەم 4 .قىسىم  (ئاۋازلىق ئەسەر)",
                "url": "static/Baldur Oyghan'ghan Adem/بالدۇر ئويغانغان ئادەم 4 .قىسىم  (ئاۋازلىق ئەسەر).mp3",
                "pic": "",
                "lyric": "",
                "source": "local",
                "url_id": "3089f1bd7ea1e8ebcaea2de32093f5c5",
                "pic_id": "",
                "lyric_id": ""
            },
            {
                "id": "6d2579f331cb5d00eb9b8b5c9a1e2682",
                "name": "بالدۇر ئويغانغان ئادەم 11 .قىسىم  (ئاۋازلىق ئەسەر)",
                "artist": "ئاۋازلىق ئەسەر Awazliq Eser",
                "album": "بالدۇر ئويغانغان ئادەم 11 .قىسىم  (ئاۋازلىق ئەسەر)",
                "url": "static/Baldur Oyghan'ghan Adem/بالدۇر ئويغانغان ئادەم 11 .قىسىم  (ئاۋازلىق ئەسەر).mp3",
                "pic": "",
                "lyric": "",
                "source": "local",
                "url_id": "6d2579f331cb5d00eb9b8b5c9a1e2682",
                "pic_id": "",
                "lyric_id": ""
            },
            {
                "id": "90bfd7a07eb91183c990ceb39540b685",
                "name": "بالدۇر ئويغانغان ئادەم 2 .قىسىم  (ئاۋازلىق ئەسەر)",
                "artist": "ئاۋازلىق ئەسەر Awazliq Eser",
                "album": "بالدۇر ئويغانغان ئادەم 2 .قىسىم  (ئاۋازلىق ئەسەر)",
                "url": "static/Baldur Oyghan'ghan Adem/بالدۇر ئويغانغان ئادەم 2 .قىسىم  (ئاۋازلىق ئەسەر).mp3",
                "pic": "",
                "lyric": "",
                "source": "local",
                "url_id": "90bfd7a07eb91183c990ceb39540b685",
                "pic_id": "",
                "lyric_id": ""
            },
            {
                "id": "4033e78e90eff5e6f391928f9bab75ee",
                "name": "بالدۇر ئويغانغان ئادەم 13 .قىسىم  (ئاۋازلىق ئەسەر)",
                "artist": "ئاۋازلىق ئەسەر Awazliq Eser",
                "album": "بالدۇر ئويغانغان ئادەم 13 .قىسىم  (ئاۋازلىق ئەسەر)",
                "url": "static/Baldur Oyghan'ghan Adem/بالدۇر ئويغانغان ئادەم 13 .قىسىم  (ئاۋازلىق ئەسەر).mp3",
                "pic": "",
                "lyric": "",
                "source": "local",
                "url_id": "4033e78e90eff5e6f391928f9bab75ee",
                "pic_id": "",
                "lyric_id": ""
            },
            {
                "id": "5710d08b3bde7f1046ca0a39161ef017",
                "name": "بالدۇر ئويغانغان ئادەم 10 .قىسىم  (ئاۋازلىق ئەسەر)",
                "artist": "ئاۋازلىق ئەسەر Awazliq Eser",
                "album": "بالدۇر ئويغانغان ئادەم 10 .قىسىم  (ئاۋازلىق ئەسەر)",
                "url": "static/Baldur Oyghan'ghan Adem/بالدۇر ئويغانغان ئادەم 10 .قىسىم  (ئاۋازلىق ئەسەر).mp3",
                "pic": "",
                "lyric": "",
                "source": "local",
                "url_id": "5710d08b3bde7f1046ca0a39161ef017",
                "pic_id": "",
                "lyric_id": ""
            },
            {
                "id": "ae4173b07c251404015ee9f449486d4a",
                "name": "بالدۇر ئويغانغان ئادەم 15 .قىسىم  (ئاۋازلىق ئەسەر)",
                "artist": "ئاۋازلىق ئەسەر Awazliq Eser",
                "album": "بالدۇر ئويغانغان ئادەم 15 .قىسىم  (ئاۋازلىق ئەسەر)",
                "url": "static/Baldur Oyghan'ghan Adem/بالدۇر ئويغانغان ئادەم 15 .قىسىم  (ئاۋازلىق ئەسەر).mp3",
                "pic": "",
                "lyric": "",
                "source": "local",
                "url_id": "ae4173b07c251404015ee9f449486d4a",
                "pic_id": "",
                "lyric_id": ""
            },
            {
                "id": "b972e561aed0abeaadccbfad3cd94a61",
                "name": "بالدۇر ئويغانغان ئادەم 9 .قىسىم  (ئاۋازلىق ئەسەر)",
                "artist": "ئاۋازلىق ئەسەر Awazliq Eser",
                "album": "بالدۇر ئويغانغان ئادەم 9 .قىسىم  (ئاۋازلىق ئەسەر)",
                "url": "static/Baldur Oyghan'ghan Adem/بالدۇر ئويغانغان ئادەم 9 .قىسىم  (ئاۋازلىق ئەسەر).mp3",
                "pic": "",
                "lyric": "",
                "source": "local",
                "url_id": "b972e561aed0abeaadccbfad3cd94a61",
                "pic_id": "",
                "lyric_id": ""
            },
            {
                "id": "d974e2481333b93a020dacd0bbb4dc7f",
                "name": "بالدۇر ئويغانغان ئادەم 6 .قىسىم  (ئاۋازلىق ئەسەر)",
                "artist": "ئاۋازلىق ئەسەر Awazliq Eser",
                "album": "بالدۇر ئويغانغان ئادەم 6 .قىسىم  (ئاۋازلىق ئەسەر)",
                "url": "static/Baldur Oyghan'ghan Adem/بالدۇر ئويغانغان ئادەم 6 .قىسىم  (ئاۋازلىق ئەسەر).mp3",
                "pic": "",
                "lyric": "",
                "source": "local",
                "url_id": "d974e2481333b93a020dacd0bbb4dc7f",
                "pic_id": "",
                "lyric_id": ""
            },
            {
                "id": "6c92b3f49e52a07ebdfeb6d3b6c2760c",
                "name": "بالدۇر ئويغانغان ئادەم 5 .قىسىم  (ئاۋازلىق ئەسەر)",
                "artist": "ئاۋازلىق ئەسەر Awazliq Eser",
                "album": "بالدۇر ئويغانغان ئادەم 5 .قىسىم  (ئاۋازلىق ئەسەر)",
                "url": "static/Baldur Oyghan'ghan Adem/بالدۇر ئويغانغان ئادەم 5 .قىسىم  (ئاۋازلىق ئەسەر).mp3",
                "pic": "",
                "lyric": "",
                "source": "local",
                "url_id": "6c92b3f49e52a07ebdfeb6d3b6c2760c",
                "pic_id": "",
                "lyric_id": ""
            },
            {
                "id": "f755b0517d5c41243a8a383d7b0548e2",
                "name": "بالدۇر ئويغانغان ئادەم 7 .قىسىم  (ئاۋازلىق ئەسەر)",
                "artist": "ئاۋازلىق ئەسەر Awazliq Eser",
                "album": "بالدۇر ئويغانغان ئادەم 7 .قىسىم  (ئاۋازلىق ئەسەر)",
                "url": "static/Baldur Oyghan'ghan Adem/بالدۇر ئويغانغان ئادەم 7 .قىسىم  (ئاۋازلىق ئەسەر).mp3",
                "pic": "",
                "lyric": "",
                "source": "local",
                "url_id": "f755b0517d5c41243a8a383d7b0548e2",
                "pic_id": "",
                "lyric_id": ""
            },
            {
                "id": "49f6931eede1cdd8fa9e4325dc768760",
                "name": "بالدۇر ئويغانغان ئادەم 12 .قىسىم  (ئاۋازلىق ئەسەر)",
                "artist": "ئاۋازلىق ئەسەر Awazliq Eser",
                "album": "بالدۇر ئويغانغان ئادەم 12 .قىسىم  (ئاۋازلىق ئەسەر)",
                "url": "static/Baldur Oyghan'ghan Adem/بالدۇر ئويغانغان ئادەم 12 .قىسىم  (ئاۋازلىق ئەسەر).mp3",
                "pic": "",
                "lyric": "",
                "source": "local",
                "url_id": "49f6931eede1cdd8fa9e4325dc768760",
                "pic_id": "",
                "lyric_id": ""
            },
            {
                "id": "f658a7b8a26f2f15ba023e2aa5dd2e36",
                "name": "بالدۇر ئويغانغان ئادەم  14 .قىسىم  (ئاۋازلىق ئەسەر)",
                "artist": "ئاۋازلىق ئەسەر Awazliq Eser",
                "album": "بالدۇر ئويغانغان ئادەم  14 .قىسىم  (ئاۋازلىق ئەسەر)",
                "url": "static/Baldur Oyghan'ghan Adem/بالدۇر ئويغانغان ئادەم  14 .قىسىم  (ئاۋازلىق ئەسەر).mp3",
                "pic": "",
                "lyric": "",
                "source": "local",
                "url_id": "f658a7b8a26f2f15ba023e2aa5dd2e36",
                "pic_id": "",
                "lyric_id": ""
            },
            {
                "id": "5749f4767c810ac5b54edd71d0eed9e8",
                "name": "بالدۇر ئويغانغان ئادەم 8 .قىسىم  (ئاۋازلىق ئەسەر)",
                "artist": "ئاۋازلىق ئەسەر Awazliq Eser",
                "album": "بالدۇر ئويغانغان ئادەم 8 .قىسىم  (ئاۋازلىق ئەسەر)",
                "url": "static/Baldur Oyghan'ghan Adem/بالدۇر ئويغانغان ئادەم 8 .قىسىم  (ئاۋازلىق ئەسەر).mp3",
                "pic": "",
                "lyric": "",
                "source": "local",
                "url_id": "5749f4767c810ac5b54edd71d0eed9e8",
                "pic_id": "",
                "lyric_id": ""
            },
            {
                "id": "b22a1dfb8672d91378d6ada62f64bdc8",
                "name": "بالدۇر ئويغانغان ئادەم 16 .قىسىم   ئاخىرقى قىسىم (ئاۋازلىق ئەسەر)",
                "artist": "ئاۋازلىق ئەسەر Awazliq Eser",
                "album": "بالدۇر ئويغانغان ئادەم 16 .قىسىم   ئاخىرقى قىسىم (ئاۋازلىق ئەسەر)",
                "url": "static/Baldur Oyghan'ghan Adem/بالدۇر ئويغانغان ئادەم 16 .قىسىم   ئاخىرقى قىسىم (ئاۋازلىق ئەسەر).mp3",
                "pic": "",
                "lyric": "",
                "source": "local",
                "url_id": "b22a1dfb8672d91378d6ada62f64bdc8",
                "pic_id": "",
                "lyric_id": ""
            },
            {
                "id": "278c31a33dbe74aa9a8b31d787dfb462",
                "name": "بالدۇر ئويغانغان ئادەم 1 .قىسىم  (ئاۋازلىق ئەسەر)",
                "artist": "ئاۋازلىق ئەسەر Awazliq Eser",
                "album": "بالدۇر ئويغانغان ئادەم 1 .قىسىم  (ئاۋازلىق ئەسەر)",
                "url": "static/Baldur Oyghan'ghan Adem/بالدۇر ئويغانغان ئادەم 1 .قىسىم  (ئاۋازلىق ئەسەر).mp3",
                "pic": "",
                "lyric": "",
                "source": "local",
                "url_id": "278c31a33dbe74aa9a8b31d787dfb462",
                "pic_id": "",
                "lyric_id": ""
            }
        ]
    }
]